free_proxies_scraper/__init__.py
free_proxies_scraper/core/__init__.py
free_proxies_scraper/core/base_scraper.py
free_proxies_scraper/core/http_scraper.py
free_proxies_scraper/parser/__init__.py
free_proxies_scraper/parser/base_parser.py
free_proxies_scraper/parser/html_parser.py
free_proxies_scraper/proxy/__init__.py
free_proxies_scraper/proxy/free_proxy_provider.py
free_proxies_scraper/proxy/proxy_manager.py
free_proxies_scraper/proxy/proxy_provider.py
free_proxies_scraper/storage/__init__.py
free_proxies_scraper/storage/base_storage.py
free_proxies_scraper/storage/csv_storage.py
free_proxies_scraper/utils/__init__.py
free_proxies_scraper/utils/user_agent.py
free_proxies_scraper-0.1.2.dist-info/licenses/LICENSE
free_proxies_scraper-0.1.2.dist-info/METADATA
free_proxies_scraper-0.1.2.dist-info/WHEEL
free_proxies_scraper-0.1.2.dist-info/top_level.txt
free_proxies_scraper-0.1.2.dist-info/RECORD
